MTP/__init__.py
MTP/cli.py
MTP/handlers.py
MTP/parse.py
MTP/transformers.py
mparsett-0.1.0.dist-info/METADATA
mparsett-0.1.0.dist-info/WHEEL
mparsett-0.1.0.dist-info/entry_points.txt
mparsett-0.1.0.dist-info/RECORD
