Metadata-Version: 2.3
Name: mparsett
Version: 0.1.0
Summary: Music Torrent Parser
License: MIT
Author: Dreu LaVelle
Author-email: dreu.lavelle@gmail.com
Requires-Python: >=3.11,<4.0
Classifier: License :: OSI Approved :: MIT License
Classifier: Programming Language :: Python :: 3
Classifier: Programming Language :: Python :: 3.11
Classifier: Programming Language :: Python :: 3.12
Classifier: Programming Language :: Python :: 3.13
Requires-Dist: arrow (>=1.3.0,<2.0.0)
Requires-Dist: regex (>=2024.11.6,<2025.0.0)
